pandas_alchemy/__init__.py
pandas_alchemy/alchemy.py
pandas_alchemy/base.py
pandas_alchemy/coercion.py
pandas_alchemy/db.py
pandas_alchemy/dialect.py
pandas_alchemy/generic.py
pandas_alchemy/indexer.py
pandas_alchemy/ops_mixin.py
pandas_alchemy/utils.py
pandas_alchemy-0.0.2.dist-info/LICENSE
pandas_alchemy-0.0.2.dist-info/METADATA
pandas_alchemy-0.0.2.dist-info/WHEEL
pandas_alchemy-0.0.2.dist-info/top_level.txt
pandas_alchemy-0.0.2.dist-info/RECORD
