Metadata-Version: 2.1
Name: pandas-alchemy
Version: 0.0.2
Summary: SQL based, pandas compatible DataFrame & Series
Home-page: https://github.com/JunyuanChen/pandas-alchemy
Author: Junyuan Chen
Author-email: junyuan.chen.c@gmail.com
License: MIT
Platform: UNKNOWN
Classifier: Development Status :: 2 - Pre-Alpha
Classifier: Intended Audience :: Developers
Classifier: Intended Audience :: Information Technology
Classifier: Intended Audience :: Science/Research
Classifier: License :: OSI Approved :: MIT License
Classifier: Programming Language :: Python :: 3
Classifier: Operating System :: OS Independent
Classifier: Topic :: Database
Classifier: Topic :: Scientific/Engineering
Classifier: Topic :: Scientific/Engineering :: Information Analysis
